cardsort/__init__.py
cardsort/analysis.py
cardsort-0.2.45.dist-info/LICENSE
cardsort-0.2.45.dist-info/METADATA
cardsort-0.2.45.dist-info/WHEEL
cardsort-0.2.45.dist-info/RECORD
